qtpie/__init__.py
qtpie/app.py
qtpie/py.typed
qtpie/screen.py
qtpie/state.py
qtpie/widget_base.py
qtpie/bindings/__init__.py
qtpie/bindings/bind.py
qtpie/bindings/registry.py
qtpie/cli/__init__.py
qtpie/cli/main.py
qtpie/cli/tr.py
qtpie/decorators/__init__.py
qtpie/decorators/_async_wrap.py
qtpie/decorators/action.py
qtpie/decorators/entrypoint.py
qtpie/decorators/menu.py
qtpie/decorators/slot.py
qtpie/decorators/stylesheet.py
qtpie/decorators/widget.py
qtpie/decorators/window.py
qtpie/factories/__init__.py
qtpie/factories/make.py
qtpie/factories/separator.py
qtpie/factories/spacer.py
qtpie/styles/__init__.py
qtpie/styles/classes.py
qtpie/styles/color_scheme.py
qtpie/styles/compiler.py
qtpie/styles/loader.py
qtpie/styles/watcher.py
qtpie/testing/__init__.py
qtpie/testing/driver.py
qtpie/testing/plugin.py
qtpie/translations/__init__.py
qtpie/translations/compiler.py
qtpie/translations/loader.py
qtpie/translations/parser.py
qtpie/translations/store.py
qtpie/translations/translatable.py
qtpie/translations/watcher.py
qtpie/widgets/__init__.py
qtpie/widgets/filterable_dropdown.py
qtpie/widgets/filterable_dropdown_with_description.py
qtpie-0.1.10.dist-info/METADATA
qtpie-0.1.10.dist-info/WHEEL
qtpie-0.1.10.dist-info/entry_points.txt
qtpie-0.1.10.dist-info/RECORD
