Metadata-Version: 2.4
Name: qtpie
Version: 0.1.10
Summary: Tasty way to build Qt apps
Project-URL: Documentation, https://mrowrlib.github.io/qtpie
Project-URL: Homepage, https://mrowrlib.github.io/qtpie
Project-URL: Repository, https://github.com/MrowrLib/QtPie
Author-email: Mrowr Purr <mrowr.purr@gmail.com>
License: 0BSD
Keywords: declarative,desktop,framework,gui,pyqt,pyside6,qt,reactive,ui,widgets
Classifier: Operating System :: OS Independent
Classifier: Programming Language :: Python :: 3
Classifier: Programming Language :: Python :: 3.13
Requires-Python: >=3.13
Requires-Dist: mrowrpurr-pyscss>=1.4.1
Requires-Dist: observant>=0.1.5
Requires-Dist: pyyaml>=6.0
Requires-Dist: qasync>=0.27.1
Requires-Dist: qtpy>=2.4.3
Requires-Dist: typer>=0.12
Provides-Extra: test
Requires-Dist: pytest; extra == 'test'
Requires-Dist: pytest-qt; extra == 'test'
